MANIFEST.in
README.md
setup.py
klassify/__init__.py
klassify/__main__.py
klassify/klassify.py
klassify.egg-info/PKG-INFO
klassify.egg-info/SOURCES.txt
klassify.egg-info/dependency_links.txt
klassify.egg-info/requires.txt
klassify.egg-info/top_level.txt
klassify/backend/__init__.py
klassify/backend/handlers.py
klassify/backend/tokenizer.py
klassify/dist/base.css
klassify/dist/bundle.js
klassify/interface/index.html