Metadata-Version: 1.1
Name: klassify
Version: 0.6
Summary: Redis based text classification service
Home-page: https://github.com/fatiherikli/klassify
Author: Fatih Erikli
Author-email: fatiherikli@gmail.com
License: UNKNOWN
Platform: UNKNOWN
Classifier: Environment :: Web Environment
